emp_mos_api/__init__.py
emp_mos_api/mos.py
emp_mos_api/examples/__init__.py
emp_mos_api/examples/read_car_fine.py
emp_mos_api/examples/read_electro_epd.py
emp_mos_api/examples/read_flat.py
emp_mos_api/examples/read_profile.py
emp_mos_api/examples/read_watermeters.py
emp_mos_api-0.12.dist-info/METADATA
emp_mos_api-0.12.dist-info/RECORD
emp_mos_api-0.12.dist-info/WHEEL
emp_mos_api-0.12.dist-info/pbr.json
emp_mos_api-0.12.dist-info/top_level.txt
