Metadata-Version: 2.1
Name: emp-mos-api
Version: 0.12
Summary: Неофициальный Python клиент Единой мобильной платформы города Москвы.
Home-page: https://github.com/dontsovcmc/emp_mos_api
Author: Dontsov E.
Author-email: dontsovcmc@gmail.com
License: MIT
Platform: linux2
Platform: win32
Classifier: Programming Language :: Python :: 2.7
Classifier: Programming Language :: Python :: 3
Classifier: License :: OSI Approved :: MIT License
Classifier: Operating System :: OS Independent
Requires-Dist: requests (>=2.19.1)
